molten_mail/__init__.py
molten_mail/exceptions.py
molten_mail/mail.py
molten_mail/templates.py
molten_mail-0.1.0.dist-info/LICENSE
molten_mail-0.1.0.dist-info/METADATA
molten_mail-0.1.0.dist-info/WHEEL
molten_mail-0.1.0.dist-info/top_level.txt
molten_mail-0.1.0.dist-info/RECORD
