Metadata-Version: 2.1
Name: molten-mail
Version: 0.1.0
Summary: A simple email component for the Molten web framework
Home-page: https://github.com/androiddrew/molten-mail
Author: Drew Bednar
Author-email: drew@androiddrew.com
License: BSD
Keywords: molten-mail molten_mail molten mail email SMTP
Platform: UNKNOWN
Classifier: Development Status :: 2 - Pre-Alpha
Classifier: Environment :: Web Environment
Classifier: Intended Audience :: Developers
Classifier: License :: OSI Approved :: BSD License
Classifier: Natural Language :: English
Classifier: Programming Language :: Python :: 3.6
Classifier: Programming Language :: Python :: 3.7
Requires-Dist: molten (>=0.7.1)
Provides-Extra: dev
Requires-Dist: pytest; extra == 'dev'
Requires-Dist: pytest-cov; extra == 'dev'
Requires-Dist: tox; extra == 'dev'
Requires-Dist: jinja2 (<3.0,>=2.10); extra == 'dev'
Provides-Extra: templates
Requires-Dist: jinja2 (<3.0,>=2.10); extra == 'templates'
